findcrashedcodedeveloper/__init__.py
findcrashedcodedeveloper/__main__.py
findcrashedcodedeveloper/constants.py
findcrashedcodedeveloper/githubapi/__init__.py
findcrashedcodedeveloper/githubapi/blames.py
findcrashedcodedeveloper/githubapi/client.py
findcrashedcodedeveloper/githubapi/files.py
findcrashedcodedeveloper/githubapi/models/__init__.py
findcrashedcodedeveloper/githubapi/models/blame.py
findcrashedcodedeveloper/githubapi/models/exceptions.py
findcrashedcodedeveloper/githubapi/models/file.py
findcrashedcodedeveloper/githubapi/models/line.py
findcrashedcodedeveloper/githubapi/models/repository.py
findcrashedcodedeveloper/githubapi/models/user.py
findcrashedcodedeveloper/models/__init__.py
findcrashedcodedeveloper/models/repository_info.py
findcrashedcodedeveloper/sentryapi/__init__.py
findcrashedcodedeveloper/sentryapi/client.py
findcrashedcodedeveloper/sentryapi/events.py
findcrashedcodedeveloper/sentryapi/issues.py
findcrashedcodedeveloper/sentryapi/models/__init__.py
findcrashedcodedeveloper/sentryapi/models/event.py
findcrashedcodedeveloper/sentryapi/models/issue.py
findcrashedcodedeveloper/sentryapi/models/stacktrace.py
findcrashedcodedeveloper/utilities/__init__.py
findcrashedcodedeveloper/utilities/codedeveloper.py
findcrashedcodedeveloper/utilities/filepath.py
findcrashedcodedeveloper/utilities/files.py
findcrashedcodedeveloper/utilities/sentrystacktrace.py
findcrashedcodedeveloper/viewer/__init__.py
findcrashedcodedeveloper/viewer/author.py
findcrashedcodedeveloper/viewer/stack_trace.py
findcrashedcodedeveloper-0.1.0.dist-info/METADATA
findcrashedcodedeveloper-0.1.0.dist-info/WHEEL
findcrashedcodedeveloper-0.1.0.dist-info/entry_points.txt
findcrashedcodedeveloper-0.1.0.dist-info/top_level.txt
findcrashedcodedeveloper-0.1.0.dist-info/RECORD
