Metadata-Version: 2.1
Name: findcrashedcodedeveloper
Version: 0.1.0
Summary: Find the developer responsible for crashed code from stack trace
Home-page: https://github.com/karambir252/findcrashedcodedeveloper
Author: Karambir Gahlot
Author-email: karambir252@gmail.com
License: MIT
Platform: UNKNOWN
Classifier: License :: OSI Approved :: MIT License
Classifier: Programming Language :: Python
Classifier: Programming Language :: Python :: 2
Classifier: Programming Language :: Python :: 3
Requires-Dist: graphqlclient
Requires-Dist: requests
